subspace_openapi_client/__init__.py
subspace_openapi_client/api_client.py
subspace_openapi_client/configuration.py
subspace_openapi_client/exceptions.py
subspace_openapi_client/model_utils.py
subspace_openapi_client/rest.py
subspace_openapi_client/api/__init__.py
subspace_openapi_client/api/accelerator_service_api.py
subspace_openapi_client/api/global_turn_service_api.py
subspace_openapi_client/api/sip_teleport_service_api.py
subspace_openapi_client/api/web_rtc_cdn_service_api.py
subspace_openapi_client/apis/__init__.py
subspace_openapi_client/model/__init__.py
subspace_openapi_client/model/body.py
subspace_openapi_client/model/body1.py
subspace_openapi_client/model/protobuf_any.py
subspace_openapi_client/model/v1_accelerator.py
subspace_openapi_client/model/v1_create_sip_teleport.py
subspace_openapi_client/model/v1_global_turn_response.py
subspace_openapi_client/model/v1_global_turn_server.py
subspace_openapi_client/model/v1_list_accelerator_response.py
subspace_openapi_client/model/v1_list_sip_teleport_response.py
subspace_openapi_client/model/v1_next_page.py
subspace_openapi_client/model/v1_sip_teleport_response.py
subspace_openapi_client/model/v1_sip_teleport_status.py
subspace_openapi_client/model/v1_teleport_addresses.py
subspace_openapi_client/model/v1_transport_type.py
subspace_openapi_client/model/v1_update_sip_teleport.py
subspace_openapi_client/model/v1_web_rtc_cdn_response.py
subspace_openapi_client/model/v1_web_rtc_cdn_server.py
subspace_openapi_client/models/__init__.py
subspace_openapi_client-1.0.12.dist-info/LICENSE
subspace_openapi_client-1.0.12.dist-info/METADATA
subspace_openapi_client-1.0.12.dist-info/WHEEL
subspace_openapi_client-1.0.12.dist-info/top_level.txt
subspace_openapi_client-1.0.12.dist-info/RECORD
