Metadata-Version: 2.1
Name: subspace-openapi-client
Version: 1.0.12
Summary: Subspace Product API
Home-page: https://github.com/subspace-com/subspace_python_openapi_client.git
Author: Sales
Author-email: sales@subspace.com
License: CC BY-NC-ND 4.0
Keywords: OpenAPI,OpenAPI-Generator,Subspace Product API
Platform: UNKNOWN
Requires-Python: >=3.6
License-File: LICENSE
Requires-Dist: urllib3 (>=1.25.3)
Requires-Dist: python-dateutil
